setup.py
binom/__init__.py
binom/binomialExpansion.dll
binom/newton.py
binomialExpansionNewton.egg-info/PKG-INFO
binomialExpansionNewton.egg-info/SOURCES.txt
binomialExpansionNewton.egg-info/dependency_links.txt
binomialExpansionNewton.egg-info/top_level.txt