Metadata-Version: 2.1
Name: binomialExpansionNewton
Version: 1.0
Summary: Implementacja Dwumianu Newtona
